{
  "PrimitivesFontSizeFontSize56": 56,
  "PrimitivesFontSizeFontSize48": 48,
  "PrimitivesFontSizeFontSize40": 40,
  "PrimitivesFontSizeFontSize32": 32,
  "PrimitivesFontSizeFontSize28": 28,
  "PrimitivesFontSizeFontSize24": 24,
  "PrimitivesFontSizeFontSize20": 20,
  "PrimitivesFontSizeFontSize18": 18,
  "PrimitivesFontSizeFontSize16": 16,
  "PrimitivesFontSizeFontSize14": 14,
  "PrimitivesFontSizeFontSize12": 12,
  "PrimitivesFontWeightFontWeightRegular": 400,
  "PrimitivesFontWeightFontWeightMedium": 500,
  "PrimitivesFontWeightFontWeightBold": 700,
  "PrimitivesLineHeightLineHeight120": 1.2,
  "PrimitivesLineHeightLineHeight140": 1.4,
  "PrimitivesLineHeightLineHeight150": 1.5,
  "PrimitivesLineHeightLineHeight160": 1.6,
  "PrimitivesLetterSpacingLetterSpacing0": 0,
  "PrimitivesFontFamilyNotosansjp": "Noto Sans JP",
  "PrimitivesFontFamilyRobotomono": "Roboto Mono",
  "PrimitivesColorPrimary": "rgba(7,72,207,1)",
  "PrimitivesColorPrimarySub": "rgba(0,83,255,0.1)",
  "PrimitivesColorBlack": "rgba(1,30,42,1)",
  "PrimitivesColorBlackSub": "rgba(1,30,42,0.5)",
  "PrimitivesColorBlackOverlay": "rgba(1,30,42,0.3)",
  "PrimitivesColorBlackDisabled": "rgba(1,30,42,0.2)",
  "PrimitivesColorBlack3Opacity": "rgba(1,30,42,0.03)",
  "PrimitivesColorBlack5Opacity": "rgba(1,30,42,0.05)",
  "PrimitivesColorBlack10Opacity": "rgba(1,30,42,0.1)",
  "PrimitivesColorBlack20Opacity": "rgba(1,30,42,0.2)",
  "PrimitivesColorBlack50Opacity": "rgba(1,30,42,0.5)",
  "PrimitivesColorWhite": "rgba(255,255,255,1)",
  "PrimitivesColorTransparent": "rgba(0,0,0,0)",
  "PrimitivesColorDanger": "rgba(224,6,6,1)",
  "PrimitivesColorDangerSub": "rgba(224,6,6,0.1)",
  "PrimitivesColorWarning": "rgba(207,165,17,1)",
  "PrimitivesColorSuccess": "rgba(23,179,132,1)",
  "PrimitivesColorLink": "rgba(58,58,230,1)",
  "PrimitivesColorLinkVisited": "rgba(138,74,236,1)",
  "PrimitivesShadowXLow1": 0,
  "PrimitivesShadowYLow1": 4,
  "PrimitivesShadowBlurLow1": 8,
  "PrimitivesShadowSpreadLow1": 0,
  "PrimitivesShadowColorLow1": "rgba(1,30,42,1)",
  "PrimitivesShadowAlphaLow1": 0.1,
  "PrimitivesShadowXLow2": 0,
  "PrimitivesShadowYLow2": 0,
  "PrimitivesShadowBlurLow2": 10,
  "PrimitivesShadowSpreadLow2": 0,
  "PrimitivesShadowColorLow2": "rgba(1,30,42,1)",
  "PrimitivesShadowAlphaLow2": 0.08,
  "PrimitivesShadowXHigh1": 0,
  "PrimitivesShadowYHigh1": 3,
  "PrimitivesShadowBlurHigh1": 6,
  "PrimitivesShadowSpreadHigh1": 0,
  "PrimitivesShadowColorHigh1": "rgba(1,30,42,1)",
  "PrimitivesShadowAlphaHigh1": 0.08,
  "PrimitivesShadowXHigh2": 0,
  "PrimitivesShadowYHigh2": 20,
  "PrimitivesShadowBlurHigh2": 20,
  "PrimitivesShadowSpreadHigh2": 0,
  "PrimitivesShadowColorHigh2": "rgba(1,30,42,1)",
  "PrimitivesShadowAlphaHigh2": 0.08,
  "PrimitivesShadowXHigh3": 0,
  "PrimitivesShadowYHigh3": 0,
  "PrimitivesShadowBlurHigh3": 15,
  "PrimitivesShadowSpreadHigh3": 0,
  "PrimitivesShadowColorHigh3": "rgba(1,30,42,1)",
  "PrimitivesShadowAlphaHigh3": 0.08,
  "SemanticTypographyDisplayLg": {
    "fontSize": 56,
    "fontWeight": 400,
    "lineHeight": 1.4,
    "letterSpacing": 0,
    "fontFamily": "Noto Sans JP"
  },
  "SemanticTypographyDisplayMd": {
    "fontSize": 48,
    "fontWeight": 400,
    "lineHeight": 1.4,
    "letterSpacing": 0,
    "fontFamily": "Noto Sans JP"
  },
  "SemanticTypographyHeadlineLg": {
    "fontSize": 40,
    "fontWeight": 400,
    "lineHeight": 1.2,
    "letterSpacing": 0,
    "fontFamily": "Noto Sans JP"
  },
  "SemanticTypographyHeadlineMd": {
    "fontSize": 32,
    "fontWeight": 400,
    "lineHeight": 1.2,
    "letterSpacing": 0,
    "fontFamily": "Noto Sans JP"
  },
  "SemanticTypographyTitleLg": {
    "fontSize": 28,
    "fontWeight": 400,
    "lineHeight": 1.2,
    "letterSpacing": 0,
    "fontFamily": "Noto Sans JP"
  },
  "SemanticTypographyTitleMd": {
    "fontSize": 24,
    "fontWeight": 400,
    "lineHeight": 1.4,
    "letterSpacing": 0,
    "fontFamily": "Noto Sans JP"
  },
  "SemanticTypographyTitleSm": {
    "fontSize": 20,
    "fontWeight": 400,
    "lineHeight": 1.4,
    "letterSpacing": 0,
    "fontFamily": "Noto Sans JP"
  },
  "SemanticTypographyBodyLg": {
    "fontSize": 18,
    "fontWeight": 400,
    "lineHeight": 1.5,
    "letterSpacing": 0,
    "fontFamily": "Noto Sans JP"
  },
  "SemanticTypographyBodyMd": {
    "fontSize": 16,
    "fontWeight": 400,
    "lineHeight": 1.5,
    "letterSpacing": 0,
    "fontFamily": "Noto Sans JP"
  },
  "SemanticTypographyBodySm": {
    "fontSize": 14,
    "fontWeight": 400,
    "lineHeight": 1.6,
    "letterSpacing": 0,
    "fontFamily": "Noto Sans JP"
  },
  "SemanticTypographyLabelLg": {
    "fontSize": 16,
    "fontWeight": 400,
    "lineHeight": 1.5,
    "letterSpacing": 0,
    "fontFamily": "Noto Sans JP"
  },
  "SemanticTypographyLabelMd": {
    "fontSize": 14,
    "fontWeight": 400,
    "lineHeight": 1.4,
    "letterSpacing": 0,
    "fontFamily": "Noto Sans JP"
  },
  "SemanticTypographyLabelSm": {
    "fontSize": 12,
    "fontWeight": 400,
    "lineHeight": 1.4,
    "letterSpacing": 0,
    "fontFamily": "Noto Sans JP"
  },
  "SemanticColorPrimary": "rgba(7,72,207,1)",
  "SemanticColorPrimarySub": "rgba(0,83,255,0.1)",
  "SemanticColorBlack": "rgba(1,30,42,1)",
  "SemanticColorBlackSub": "rgba(1,30,42,0.5)",
  "SemanticColorBlackOverlay": "rgba(1,30,42,0.3)",
  "SemanticColorBlackDisabled": "rgba(1,30,42,0.2)",
  "SemanticColorBlack3Opacity": "rgba(1,30,42,0.03)",
  "SemanticColorBlack5Opacity": "rgba(1,30,42,0.05)",
  "SemanticColorBlack10Opacity": "rgba(1,30,42,0.1)",
  "SemanticColorBlack20Opacity": "rgba(1,30,42,0.2)",
  "SemanticColorBlack50Opacity": "rgba(1,30,42,0.5)",
  "SemanticColorWhite": "rgba(255,255,255,1)",
  "SemanticColorTransparent": "rgba(0,0,0,0)",
  "SemanticColorDanger": "rgba(224,6,6,1)",
  "SemanticColorDangerSub": "rgba(224,6,6,0.1)",
  "SemanticColorWarning": "rgba(207,165,17,1)",
  "SemanticColorSuccess": "rgba(23,179,132,1)",
  "SemanticColorLink": "rgba(58,58,230,1)",
  "SemanticColorLinkVisited": "rgba(138,74,236,1)"
}